EasySQL/ABC.py
EasySQL/Characters.py
EasySQL/Classes.py
EasySQL/Constraints.py
EasySQL/Decorators.py
EasySQL/EasyInstances.py
EasySQL/Exceptions.py
EasySQL/Logging.py
EasySQL/Types.py
EasySQL/Where.py
EasySQL/__init__.py
pyeasysql-4.0.0.dist-info/LICENSE.md
pyeasysql-4.0.0.dist-info/METADATA
pyeasysql-4.0.0.dist-info/WHEEL
pyeasysql-4.0.0.dist-info/top_level.txt
pyeasysql-4.0.0.dist-info/RECORD
