Metadata-Version: 2.2
Name: pyeasysql
Version: 4.0.0
Summary: SQL Database management without even a SQL line
Author-email: Ashenguard <ashenguard@agmstudio.xyz>
Project-URL: Homepage, https://github.com/agm-studio/easysql
Project-URL: Bug Tracker, https://github.com/agm-studio/easysql/issues
Classifier: Programming Language :: Python :: 3
Classifier: License :: OSI Approved :: MIT License
Classifier: Development Status :: 5 - Production/Stable
Classifier: Operating System :: OS Independent
Requires-Python: >=3.9
License-File: LICENSE.md
Requires-Dist: mysql-connector
